airo_tulip/__init__.py
airo_tulip/api/__init__.py
airo_tulip/api/client.py
airo_tulip/api/messages.py
airo_tulip/api/server.py
airo_tulip/hardware/__init__.py
airo_tulip/hardware/constants.py
airo_tulip/hardware/ethercat.py
airo_tulip/hardware/platform_driver.py
airo_tulip/hardware/platform_monitor.py
airo_tulip/hardware/robile_platform.py
airo_tulip/hardware/structs.py
airo_tulip/hardware/util.py
airo_tulip/hardware/controllers/__init__.py
airo_tulip/hardware/controllers/controller.py
airo_tulip/hardware/controllers/velocity_platform_controller.py
airo_tulip-0.4.0.dist-info/licenses/LICENSE
examples/compliant_mode.py
examples/velocity_mode.py
airo_tulip-0.4.0.dist-info/METADATA
airo_tulip-0.4.0.dist-info/WHEEL
airo_tulip-0.4.0.dist-info/top_level.txt
airo_tulip-0.4.0.dist-info/RECORD
