Metadata-Version: 2.4
Name: airo-tulip
Version: 0.4.0
Summary: Python driver for the KELO Robile platform based on KELO tulip.
Author-email: Mathieu De Coster <mathieu.decoster@ugent.be>, Thomas Van Acker <thovacke.vanacker@ugent.be>
Project-URL: Homepage, https://github.com/airo-ugent/airo-tulip
Project-URL: Issues, https://github.com/airo-ugent/airo-tulip/issues
Classifier: Programming Language :: Python :: 3
Classifier: License :: OSI Approved :: MIT License
Classifier: Operating System :: OS Independent
Requires-Python: >=3.9
License-File: LICENSE
Requires-Dist: loguru>=0.7.2
Requires-Dist: pysoem>=1.1.6
Requires-Dist: numpy
Requires-Dist: pyzmq==26.0.3
Requires-Dist: pykalman==0.9.7
Requires-Dist: pyserial==3.5
Requires-Dist: airo-typing>=2025.4.0
Dynamic: license-file
